mypysql/__init__.py
mypysql/alchemy.py
mypysql/get_login.py
mypysql/get_tables.py
mypysql/sql.py
mypysql/table_config.py
mypysql-0.1.7.dist-info/LICENSE.md
mypysql-0.1.7.dist-info/METADATA
mypysql-0.1.7.dist-info/WHEEL
mypysql-0.1.7.dist-info/top_level.txt
mypysql-0.1.7.dist-info/RECORD
